pynnacle/__init__.py
pynnacle/config.ini
pynnacle/pynnacle.py
pynnacle-1.1.2.dist-info/AUTHORS.md
pynnacle-1.1.2.dist-info/LICENSE
pynnacle-1.1.2.dist-info/METADATA
pynnacle-1.1.2.dist-info/WHEEL
pynnacle-1.1.2.dist-info/entry_points.txt
pynnacle-1.1.2.dist-info/top_level.txt
pynnacle-1.1.2.dist-info/RECORD
